iflow_mcp_ruijian_zha_notion_mcp/__init__.py
iflow_mcp_ruijian_zha_notion_mcp/__main__.py
iflow_mcp_ruijian_zha_notion_mcp/server.py
iflow_mcp_ruijian_zha_notion_mcp/test.py
iflow_mcp_ruijian_zha_notion_mcp-0.1.3.dist-info/METADATA
iflow_mcp_ruijian_zha_notion_mcp-0.1.3.dist-info/WHEEL
iflow_mcp_ruijian_zha_notion_mcp-0.1.3.dist-info/entry_points.txt
iflow_mcp_ruijian_zha_notion_mcp-0.1.3.dist-info/licenses/LICENSE
iflow_mcp_ruijian_zha_notion_mcp-0.1.3.dist-info/RECORD
