Metadata-Version: 2.4
Name: iflow-mcp_ruijian-zha_notion_mcp
Version: 0.1.3
Summary: Notion MCP integration for todo lists
License-File: LICENSE
Requires-Python: >=3.10
Requires-Dist: httpx
Requires-Dist: mcp
